{
    "publication": "demography_2023-q1",
    "publication_type": "demography",
    "release_date": "2023-05-11",
    "frequency": "QUARTERLY",
    "geography": [
        "STATE",
        "NATIONAL"
    ],
    "demography": [
        "SEX",
        "AGE",
        "ETHNICITY",
        "NATIONALITY"
    ],
    "en": {
        "title": "[1Q 2023] Demography",
        "publication_type_title": "Demography",
        "description": "Quarterly summary of the current population and its structure, including live births and deaths for the latest quarter.",
        "resources": [
            {
                "resource_id": 1,
                "resource_type": "pdf",
                "resource_name": "Demography: 1Q 2023",
                "resource_link": "https://storage.dosm.gov.my/demography/demography_2023-q1.pdf"
            }
        ]
    },
    "bm": {
        "title": "[ST1 2023] Demografi",
        "publication_type_title": "Demografi",
        "description": "Ringkasan suku tahunan penduduk semasa dan strukturnya, termasuk kelahiran hidup dan kematian bagi suku tahun terkini.",
        "resources": [
            {
                "resource_id": 1,
                "resource_type": "pdf",
                "resource_name": "Demografi: ST1 2023",
                "resource_link": "https://storage.dosm.gov.my/demography/demography_2023-q1.pdf"
            }
        ]
    }
}